pyDaRUS/__init__.py
pyDaRUS/pydarus_server.py
pyDaRUS/metadatablocks/__init__.py
pyDaRUS/metadatablocks/archive.py
pyDaRUS/metadatablocks/astrophysics.py
pyDaRUS/metadatablocks/biomedical.py
pyDaRUS/metadatablocks/citation.py
pyDaRUS/metadatablocks/codeMeta.py
pyDaRUS/metadatablocks/engMeta.py
pyDaRUS/metadatablocks/enzymeML.py
pyDaRUS/metadatablocks/geospatial.py
pyDaRUS/metadatablocks/journal.py
pyDaRUS/metadatablocks/privacy.py
pyDaRUS/metadatablocks/process.py
pyDaRUS/metadatablocks/socialscience.py
pyDaRUS-1.0.5.dist-info/LICENSE
pyDaRUS-1.0.5.dist-info/METADATA
pyDaRUS-1.0.5.dist-info/WHEEL
pyDaRUS-1.0.5.dist-info/top_level.txt
pyDaRUS-1.0.5.dist-info/RECORD
