Metadata-Version: 2.1
Name: pyDaRUS
Version: 1.0.5
Author: easyDataverse
License: MIT License
License-File: LICENSE
Requires-Dist: easyDataverse
Requires-Dist: fastapi
Requires-Dist: uvicorn
Requires-Dist: pydantic
Requires-Dist: jinja2
Requires-Dist: pyDataverse
Requires-Dist: pandas
Requires-Dist: pyaml
